asab/__init__.py
asab/__version__.py
asab/alert.py
asab/application.py
asab/config.py
asab/contextvars.py
asab/exceptions.py
asab/log.py
asab/pdict.py
asab/pubsub.py
asab/socket.py
asab/task.py
asab/timer.py
asab/tls.py
asab/utils.py
asab/abc/__init__.py
asab/abc/module.py
asab/abc/service.py
asab/abc/singleton.py
asab/api/__init__.py
asab/api/discovery.py
asab/api/doc.py
asab/api/doc_templates.py
asab/api/internal_auth.py
asab/api/log.py
asab/api/service.py
asab/api/web_handler.py
asab/library/__init__.py
asab/library/dirsync.py
asab/library/item.py
asab/library/service.py
asab/library/providers/__init__.py
asab/library/providers/abc.py
asab/library/providers/azurestorage.py
asab/library/providers/filesystem.py
asab/library/providers/filesystem_inotify.py
asab/library/providers/git.py
asab/library/providers/libsreg.py
asab/library/providers/zookeeper.py
asab/metrics/__init__.py
asab/metrics/http.py
asab/metrics/influxdb.py
asab/metrics/metrics.py
asab/metrics/native.py
asab/metrics/openmetric.py
asab/metrics/service.py
asab/metrics/storage.py
asab/metrics/web_handler.py
asab/proactor/__init__.py
asab/proactor/service.py
asab/sentry/__init__.py
asab/sentry/service.py
asab/storage/__init__.py
asab/storage/elasticsearch.py
asab/storage/exceptions.py
asab/storage/inmemory.py
asab/storage/mongodb.py
asab/storage/service.py
asab/storage/upsertor.py
asab/web/__init__.py
asab/web/accesslog.py
asab/web/container.py
asab/web/metrics.py
asab/web/service.py
asab/web/staticdir.py
asab/web/webcrypto.py
asab/web/websocket.py
asab/web/auth/__init__.py
asab/web/auth/authorization.py
asab/web/auth/decorator.py
asab/web/auth/service.py
asab/web/auth/utils.py
asab/web/auth/providers/__init__.py
asab/web/auth/providers/abc.py
asab/web/auth/providers/access_token.py
asab/web/auth/providers/id_token.py
asab/web/auth/providers/mock.py
asab/web/auth/providers/key_providers/__init__.py
asab/web/auth/providers/key_providers/abc.py
asab/web/auth/providers/key_providers/static.py
asab-25.15.dist-info/licenses/LICENSE
asab-25.15.dist-info/METADATA
asab-25.15.dist-info/WHEEL
asab-25.15.dist-info/top_level.txt
asab-25.15.dist-info/RECORD
