Metadata-Version: 2.4
Name: asab
Version: 25.15
Summary: ASAB simplifies the development of async application servers
Home-page: https://github.com/TeskaLabs/asab
Author: TeskaLabs Ltd
Author-email: info@teskalabs.com
License: BSD License
Project-URL: Source, https://github.com/TeskaLabs/asab
Keywords: asyncio
Platform: any
Classifier: Development Status :: 5 - Production/Stable
Classifier: Programming Language :: Python :: 3.9
Classifier: Programming Language :: Python :: 3.10
Classifier: Programming Language :: Python :: 3.11
Classifier: Programming Language :: Python :: 3.12
Classifier: Programming Language :: Python :: 3.13
License-File: LICENSE
Requires-Dist: aiohttp<4,>=3.8.3
Requires-Dist: fastjsonschema<3,>=2.16.2
Requires-Dist: kazoo<3,>=2.9.0
Requires-Dist: PyYAML<7,>=6.0
Provides-Extra: git
Requires-Dist: pygit2<1.12; extra == "git"
Provides-Extra: encryption
Requires-Dist: cryptography; extra == "encryption"
Provides-Extra: authz
Requires-Dist: jwcrypto==1.5.6; extra == "authz"
Provides-Extra: monitoring
Requires-Dist: sentry-sdk==1.45.0; extra == "monitoring"
Dynamic: author
Dynamic: author-email
Dynamic: classifier
Dynamic: description
Dynamic: home-page
Dynamic: keywords
Dynamic: license
Dynamic: license-file
Dynamic: platform
Dynamic: project-url
Dynamic: provides-extra
Dynamic: requires-dist
Dynamic: summary
